ocr2pdf/__init__.py
ocr2pdf/ocr2pdf.py
ocr2pdf/utils.py
ocr2pdf-0.1.0.dist-info/METADATA
ocr2pdf-0.1.0.dist-info/WHEEL
ocr2pdf-0.1.0.dist-info/top_level.txt
ocr2pdf-0.1.0.dist-info/zip-safe
ocr2pdf-0.1.0.dist-info/RECORD
