Metadata-Version: 2.1
Name: ocr2pdf
Version: 0.1.0
Summary: Combines OCR output with images to make searchable pdf
Home-page: UNKNOWN
License: UNKNOWN
Keywords: searchable pdf
Platform: UNKNOWN
Classifier: Programming Language :: Python :: 3
Classifier: License :: OSI Approved :: Mozilla Public License 2.0 (MPL 2.0)
Classifier: Operating System :: OS Independent
Requires-Python: >=3.6
Requires-Dist: lxml
Requires-Dist: pandas
Requires-Dist: Pillow
Requires-Dist: pypdf2
Requires-Dist: reportlab
